tests/1/top.v
module top (
    input wire clk,      // Clock input
    input wire rst,      // Reset input (active high)
    output reg [3:0] q   // 4-bit counter output
);

    always @(posedge clk or posedge rst) begin
        if (rst) begin
            q <= 4'b0000; // Reset counter to 0
        end else begin
            q <= q + 1;   // Increment counter
        end
    end

endmodule

tests/1/top_tb.v
`timescale 1ns / 1ps

module top_tb;

    // Testbench signals
    reg clk;
    reg rst;
    wire [3:0] q;

    // Instantiate the top module
    top uut (
        .clk(clk),
        .rst(rst),
        .q(q)
    );

    // Clock generation
    initial begin
        clk = 0;
        forever #5 clk = ~clk; // 100MHz clock
    end

    // Test sequence
    initial begin
        // Initialize signals
        rst = 0;

        // Apply reset
        #10 rst = 1;
        #10 rst = 0;

        // Wait for some time to observe the counter
        #100;

        // Finish simulation
        $finish;
    end

    // Monitor counter value
    initial begin
        $monitor("At time %t, q = %h", $time, q);
    end

    // Dump signals to VCD file
    initial begin
        $dumpfile("top_tb.vcd");
        $dumpvars(0, top_tb);
    end

endmodule

tests/1/top_tb.vcd
$date
	Tue Aug  6 09:36:36 2024
$end
$version
	Icarus Verilog
$end
$timescale
	1ps
$end
$scope module top_tb $end
$var wire 4 ! q [3:0] $end
$var reg 1 " clk $end
$var reg 1 # rst $end
$scope module uut $end
$var wire 1 " clk $end
$var wire 1 # rst $end
$var reg 4 $ q [3:0] $end
$upscope $end
$upscope $end
$enddefinitions $end
$comment Show the parameter values. $end
$dumpall
$end
#0
$dumpvars
bx $
0#
0"
bx !
$end
#5000
1"
#10000
b0 !
b0 $
0"
1#
#15000
1"
#20000
0"
0#
#25000
b1 !
b1 $
1"
#30000
0"
#35000
b10 !
b10 $
1"
#40000
0"
#45000
b11 !
b11 $
1"
#50000
0"
#55000
b100 !
b100 $
1"
#60000
0"
#65000
b101 !
b101 $
1"
#70000
0"
#75000
b110 !
b110 $
1"
#80000
0"
#85000
b111 !
b111 $
1"
#90000
0"
#95000
b1000 !
b1000 $
1"
#100000
0"
#105000
b1001 !
b1001 $
1"
#110000
0"
#115000
b1010 !
b1010 $
1"
